mscene/__init__.py
mscene/__main__.py
mscene-0.1.4.dist-info/METADATA
mscene-0.1.4.dist-info/WHEEL
mscene-0.1.4.dist-info/entry_points.txt
mscene-0.1.4.dist-info/RECORD
