Metadata-Version: 2.4
Name: mscene
Version: 0.1.4
Summary: Science animation with Manim in Colab
Project-URL: Homepage, https://mscene.curiouswalk.com
Project-URL: Documentation, https://mscene.curiouswalk.com/docs
Project-URL: Repository, https://github.com/curiouswalk/mscene
Author: CuriousWalk
Author-email: hello@curiouswalk.com
License: MIT
Classifier: Intended Audience :: Education
Classifier: Intended Audience :: Science/Research
Classifier: License :: OSI Approved :: MIT License
Classifier: Natural Language :: English
Classifier: Operating System :: OS Independent
Classifier: Programming Language :: Python
Classifier: Topic :: Education
Classifier: Topic :: Multimedia
Classifier: Topic :: Scientific/Engineering
Requires-Dist: requests
